mhcflow/__init__.py
mhcflow/__main__.py
mhcflow/_version.py
mhcflow/cli.py
mhcflow/dumper.py
mhcflow/finalizer.py
mhcflow/fisher.py
mhcflow/helper.py
mhcflow/logger.py
mhcflow/mhcflow.py
mhcflow/realigner.py
mhcflow/runnable.py
mhcflow/tag_builder.py
mhcflow-0.2.2.dist-info/METADATA
mhcflow-0.2.2.dist-info/WHEEL
mhcflow-0.2.2.dist-info/entry_points.txt
mhcflow-0.2.2.dist-info/licenses/LICENSE
mhcflow-0.2.2.dist-info/RECORD
